MqttXieyiZhongwenban/README.md
MqttXieyiZhongwenban/__init__.py
MqttXieyiZhongwenban/__main__.py
MqttXieyiZhongwenban/file.epub
MqttXieyiZhongwenban/index.html
MqttXieyiZhongwenban/css/__init__.py
MqttXieyiZhongwenban/css/annotations.css
MqttXieyiZhongwenban/css/main.css
MqttXieyiZhongwenban/css/normalize.css
MqttXieyiZhongwenban/css/popup.css
MqttXieyiZhongwenban/font/__init__.py
MqttXieyiZhongwenban/font/fontello.eot
MqttXieyiZhongwenban/font/fontello.svg
MqttXieyiZhongwenban/font/fontello.ttf
MqttXieyiZhongwenban/font/fontello.woff
MqttXieyiZhongwenban/img/__init__.py
MqttXieyiZhongwenban/img/annotator-glyph-sprite.png
MqttXieyiZhongwenban/img/annotator-icon-sprite.png
MqttXieyiZhongwenban/img/apple-touch-icon.png
MqttXieyiZhongwenban/img/cancelfullscreen.png
MqttXieyiZhongwenban/img/close.png
MqttXieyiZhongwenban/img/fullscreen.png
MqttXieyiZhongwenban/img/loader.gif
MqttXieyiZhongwenban/img/menu-icon.png
MqttXieyiZhongwenban/img/save.png
MqttXieyiZhongwenban/img/saved.png
MqttXieyiZhongwenban/img/settings-s.png
MqttXieyiZhongwenban/img/settings.png
MqttXieyiZhongwenban/img/star.png
MqttXieyiZhongwenban/js/__init__.py
MqttXieyiZhongwenban/js/epub.js
MqttXieyiZhongwenban/js/epub.min.js
MqttXieyiZhongwenban/js/epub.min.map
MqttXieyiZhongwenban/js/hooks.min.js
MqttXieyiZhongwenban/js/hooks.min.map
MqttXieyiZhongwenban/js/reader.js
MqttXieyiZhongwenban/js/reader.js.map
MqttXieyiZhongwenban/js/reader.min.js
MqttXieyiZhongwenban/js/reader.min.map
MqttXieyiZhongwenban/js/hooks/__init__.py
MqttXieyiZhongwenban/js/hooks/extensions/__init__.py
MqttXieyiZhongwenban/js/hooks/extensions/highlight.js
MqttXieyiZhongwenban/js/libs/__init__.py
MqttXieyiZhongwenban/js/libs/jquery.min.js
MqttXieyiZhongwenban/js/libs/localforage.min.js
MqttXieyiZhongwenban/js/libs/screenfull.js
MqttXieyiZhongwenban/js/libs/screenfull.min.js
MqttXieyiZhongwenban/js/libs/zip.min.js
MqttXieyiZhongwenban/js/plugins/__init__.py
MqttXieyiZhongwenban/js/plugins/hypothesis.js
mqtt_xieyi_zhongwenban-2024.3.2.0.dist-info/METADATA
mqtt_xieyi_zhongwenban-2024.3.2.0.dist-info/WHEEL
mqtt_xieyi_zhongwenban-2024.3.2.0.dist-info/entry_points.txt
mqtt_xieyi_zhongwenban-2024.3.2.0.dist-info/top_level.txt
mqtt_xieyi_zhongwenban-2024.3.2.0.dist-info/RECORD
